custom_user_profiles/__init__.py
custom_user_profiles/managers.py
custom_user_profiles/models.py
custom_user_profiles-1.2.0.dist-info/DESCRIPTION.rst
custom_user_profiles-1.2.0.dist-info/METADATA
custom_user_profiles-1.2.0.dist-info/metadata.json
custom_user_profiles-1.2.0.dist-info/RECORD
custom_user_profiles-1.2.0.dist-info/top_level.txt
custom_user_profiles-1.2.0.dist-info/WHEEL
