Metadata-Version: 2.0
Name: custom-user-profiles
Version: 1.2.0
Summary: Create custom-user profiles easily
Home-page: https://github.com/laginha/custom-user-profiles
Author: Diogo Laginha
Author-email: diogo.laginha.machado@gmail.com
License: MIT
Platform: UNKNOWN
Classifier: License :: OSI Approved :: MIT License
Classifier: Programming Language :: Python :: 2
Classifier: Intended Audience :: Developers
Requires-Dist: django
Requires-Dist: django-custom-user
